LICENSE.txt
MANIFEST.in
README.md
pyproject.toml
setup.py
.tox/Cython/lib/python3.6/site-packages/Cython/Runtime/refnanny.pyx
.tox/Cython/lib/python3.6/site-packages/Cython/Utility/CConvert.pyx
.tox/Cython/lib/python3.6/site-packages/Cython/Utility/CpdefEnums.pyx
.tox/Cython/lib/python3.6/site-packages/Cython/Utility/CppConvert.pyx
.tox/Cython/lib/python3.6/site-packages/Cython/Utility/MemoryView.pyx
.tox/Cython/lib/python3.6/site-packages/Cython/Utility/TestCyUtilityLoader.pyx
.tox/Cython/lib/python3.6/site-packages/Cython/Utility/TestCythonScope.pyx
.tox/flake8/lib/python3.6/site-packages/Cython/Runtime/refnanny.pyx
.tox/flake8/lib/python3.6/site-packages/Cython/Utility/CConvert.pyx
.tox/flake8/lib/python3.6/site-packages/Cython/Utility/CpdefEnums.pyx
.tox/flake8/lib/python3.6/site-packages/Cython/Utility/CppConvert.pyx
.tox/flake8/lib/python3.6/site-packages/Cython/Utility/MemoryView.pyx
.tox/flake8/lib/python3.6/site-packages/Cython/Utility/TestCyUtilityLoader.pyx
.tox/flake8/lib/python3.6/site-packages/Cython/Utility/TestCythonScope.pyx
.tox/python3.10/lib/python3.6/site-packages/Cython/Runtime/refnanny.pyx
.tox/python3.10/lib/python3.6/site-packages/Cython/Utility/CConvert.pyx
.tox/python3.10/lib/python3.6/site-packages/Cython/Utility/CpdefEnums.pyx
.tox/python3.10/lib/python3.6/site-packages/Cython/Utility/CppConvert.pyx
.tox/python3.10/lib/python3.6/site-packages/Cython/Utility/MemoryView.pyx
.tox/python3.10/lib/python3.6/site-packages/Cython/Utility/TestCyUtilityLoader.pyx
.tox/python3.10/lib/python3.6/site-packages/Cython/Utility/TestCythonScope.pyx
.tox/python3.6/lib/python3.6/site-packages/Cython/Runtime/refnanny.pyx
.tox/python3.6/lib/python3.6/site-packages/Cython/Utility/CConvert.pyx
.tox/python3.6/lib/python3.6/site-packages/Cython/Utility/CpdefEnums.pyx
.tox/python3.6/lib/python3.6/site-packages/Cython/Utility/CppConvert.pyx
.tox/python3.6/lib/python3.6/site-packages/Cython/Utility/MemoryView.pyx
src/rivindel.egg-info/PKG-INFO
src/rivindel.egg-info/SOURCES.txt
src/rivindel.egg-info/dependency_links.txt
src/rivindel.egg-info/requires.txt
src/rivindel.egg-info/top_level.txt
