Metadata-Version: 2.1
Name: rivindel
Version: 0.0.1
Summary: RivIndel: Complex indel detection from short read sequencing
Home-page: https://github.com/bdolmo/RivIndel
Author: Bernat del Olmo
Author-email: bernatdelolmo@gmail.com
License: UNKNOWN
Keywords: complex indel detection
Platform: UNKNOWN
Classifier: Development Status :: 3 - Alpha
Classifier: Operating System :: Unix
Classifier: Programming Language :: Python :: 3.6
Classifier: Topic :: Scientific/Engineering
Classifier: Topic :: Scientific/Engineering :: Bio-Informatics
Classifier: Topic :: Scientific/Engineering :: Medical Science Apps.
Classifier: Topic :: Scientific/Engineering :: Visualization
License-File: LICENSE.txt
